nt4PAdyP/__init__.py
nt4PAdyP/add.py
nt4PAdyP2-0.0.1.dist-info/LICENSE
nt4PAdyP2-0.0.1.dist-info/METADATA
nt4PAdyP2-0.0.1.dist-info/WHEEL
nt4PAdyP2-0.0.1.dist-info/top_level.txt
nt4PAdyP2-0.0.1.dist-info/RECORD
