Metadata-Version: 2.1
Name: nt4PAdyP2
Version: 0.0.1
Summary: A small example package
Author-email: Example Author <author@example.com>
Project-URL: Homepage, https://www.baidu.com
Project-URL: Bug Tracker, https://www.google.com
Classifier: Programming Language :: Python :: 3
Classifier: License :: OSI Approved :: MIT License
Classifier: Operating System :: OS Independent
Requires-Python: >=3.2
License-File: LICENSE
Requires-Dist: requests
